speedapi_lib/__init__.py
speedapi_lib/speedapi.py
tests/__init__.py
tests/test_sample.py
speedapi_lib-0.1.4.dist-info/METADATA
speedapi_lib-0.1.4.dist-info/WHEEL
speedapi_lib-0.1.4.dist-info/entry_points.txt
speedapi_lib-0.1.4.dist-info/top_level.txt
speedapi_lib-0.1.4.dist-info/RECORD
