Metadata-Version: 2.4
Name: speedapi_lib
Version: 0.1.4
Summary: A Python library for interacting with Speed API and managing Lightning Network invoices
Home-page: https://github.com/furkankoykiran/speedapi_lib
Author: Furkan Köykıran
Author-email: furkankoykiran@gmail.com
Classifier: Programming Language :: Python :: 3
Classifier: License :: OSI Approved :: MIT License
Classifier: Operating System :: OS Independent
Requires-Python: >=3.7
Requires-Dist: requests
Requires-Dist: bolt11
Dynamic: author
Dynamic: author-email
Dynamic: classifier
Dynamic: description
Dynamic: description-content-type
Dynamic: home-page
Dynamic: requires-dist
Dynamic: requires-python
Dynamic: summary
